uuid_contour
