Metadata-Version: 1.1
Name: django-uuid-contour
Version: 0.2.1
Summary: A Django app for uuid fields
Home-page: https://github.com/japrogramer/django-uuid-contour
Author: Jorge Perez
Author-email: japrogramer@gmail.com
License: BSD
Platform: UNKNOWN
Classifier: Development Status :: 4 - Beta
Classifier: Environment :: Web Environment
Classifier: Intended Audience :: Developers
Classifier: License :: OSI Approved :: BSD License
Classifier: Operating System :: OS Independent
Classifier: Programming Language :: Python :: 3
Classifier: Framework :: Django
